LICENSE
MANIFEST.in
README.rst
setup.py
axessy/__init__.py
axessy/axessy.py
axessy.egg-info/PKG-INFO
axessy.egg-info/SOURCES.txt
axessy.egg-info/dependency_links.txt
axessy.egg-info/requires.txt
axessy.egg-info/top_level.txt