Metadata-Version: 1.1
Name: axessy
Version: 0.4
Summary: A simple packet to read and parse messages from AXESS TMC X3 devices.
Home-page: https://github.com/OpenInfoporto/axessy
Author: Infoporto La Spezia Srl
Author-email: UNKNOWN
License: GPL
Platform: UNKNOWN
Classifier: Development Status :: 3 - Alpha
Classifier: Intended Audience :: Developers
Classifier: License :: OSI Approved :: GNU General Public License (GPL)
Classifier: Operating System :: OS Independent
Classifier: Programming Language :: Python :: 2.6
Classifier: Programming Language :: Python :: 2.7
Classifier: Programming Language :: Python :: 3.2
Classifier: Programming Language :: Python :: 3.3
Classifier: Programming Language :: Python :: 3.4
Classifier: Programming Language :: Python :: 3.5
